{
  "ten_truong": "Phân hiệu Đại học Đà Nẵng tại Kon Tum",
  "url": "https://tuyensinhso.vn/diem-chuan/diem-chuan-phan-hieu-dai-hoc-da-nang-tai-kon-tum-c49166.html",
  "thoigian": "2025-08-28 11:12:04",
  "nganh": [
    {
      "stt": "1",
      "nganh": "Giáo dục Tiểu học",
      "diem": {
        "2021": {
          "thi_thpt": 23.75
        },
        "2022": {
          "thi_thpt": null
        },
        "2023": {
          "thi_thpt": 22.0
        },
        "2024": {
          "khac": 23.0
        }
      }
    },
    {
      "stt": "2",
      "nganh": "Quản lý nhà nước",
      "diem": {
        "2021": {
          "thi_thpt": 14.0
        },
        "2022": {
          "thi_thpt": 15.0
        },
        "2023": {
          "thi_thpt": 15.0
        },
        "2024": {
          "khac": 15.0
        }
      }
    },
    {
      "stt": "3",
      "nganh": "Luật kinh tế",
      "diem": {
        "2021": {
          "thi_thpt": 14.0
        },
        "2022": {
          "thi_thpt": 15.0
        },
        "2023": {
          "thi_thpt": 15.0
        },
        "2024": {
          "khac": 15.0
        }
      }
    },
    {
      "stt": "4",
      "nganh": "Quản trị kinh doanh",
      "diem": {
        "2021": {
          "thi_thpt": 14.0
        },
        "2022": {
          "thi_thpt": 15.0
        },
        "2023": {
          "thi_thpt": 15.0
        },
        "2024": {
          "khac": 15.0
        }
      }
    },
    {
      "stt": "5",
      "nganh": "Kế toán",
      "diem": {
        "2021": {
          "thi_thpt": 14.0
        },
        "2022": {
          "thi_thpt": 15.0
        },
        "2023": {
          "thi_thpt": 15.0
        },
        "2024": {
          "khac": 15.0
        }
      }
    },
    {
      "stt": "6",
      "nganh": "Công nghệ thông tin",
      "diem": {
        "2021": {
          "thi_thpt": 14.0
        },
        "2022": {
          "thi_thpt": 15.0
        },
        "2023": {
          "thi_thpt": 15.0
        },
        "2024": {
          "khac": 15.0
        }
      }
    },
    {
      "stt": "7",
      "nganh": "Ngôn ngữ Anh (2+2)",
      "diem": {
        "2021": {
          "thi_thpt": null
        },
        "2022": {
          "thi_thpt": null
        },
        "2023": {
          "thi_thpt": null
        },
        "2024": {
          "khac": 15.07
        }
      }
    },
    {
      "stt": "8",
      "nganh": "Công nghệ Kỹ thuật ô tô (2+2)",
      "diem": {
        "2021": {
          "thi_thpt": null
        },
        "2022": {
          "thi_thpt": null
        },
        "2023": {
          "thi_thpt": null
        },
        "2024": {
          "khac": 16.55
        }
      }
    },
    {
      "stt": "9",
      "nganh": "Giáo dục Mầm non",
      "diem": {
        "2021": {
          "thi_thpt": null
        },
        "2022": {
          "thi_thpt": null
        },
        "2023": {
          "thi_thpt": null
        },
        "2024": {
          "khac": null
        }
      }
    },
    {
      "stt": "10",
      "nganh": "Công nghệ kỹ thuật điều khiển và tự động hóa (2+2)",
      "diem": {
        "2021": {
          "thi_thpt": null
        },
        "2022": {
          "thi_thpt": null
        },
        "2023": {
          "thi_thpt": null
        },
        "2024": {
          "khac": null
        }
      }
    }
  ]
}