{
  "ten_truong": "Khoa Quốc Tế - Đại học Thái Nguyên",
  "ma_truong": "DTQ",
  "url": "https://vietnamnet.vn/giao-duc/diem-thi/tra-cuu-diem-chuan-cd-dh-2024/truong/khoa-quoc-te-dai-hoc-thai-nguyen?keyword=DTQ",
  "phuong_thuc_tuyen_sinh": "",
  "cac_nganh_dao_tao": [
    {
      "stt": "1",
      "nganh": "Kinh doanh quốc tế (Chương trình tiên tiến)",
      "diem_chuan": "17.00",
      "he_dao_tao": "Đại học",
      "khoi_thi": "A00,A01,D10,D01",
      "ghi_chu": "Xét duyệt điểm thi THPT"
    },
    {
      "stt": "2",
      "nganh": "Quản trị kinh doanh (Chương trình tiên tiến)",
      "diem_chuan": "17.00",
      "he_dao_tao": "Đại học",
      "khoi_thi": "A00,A01,D10,D01",
      "ghi_chu": "Xét duyệt điểm thi THPT"
    },
    {
      "stt": "3",
      "nganh": "Kế toán (Chương trình tiên tiến)",
      "diem_chuan": "17.00",
      "he_dao_tao": "Đại học",
      "khoi_thi": "A00,A01,D10,D01",
      "ghi_chu": "Xét duyệt điểm thi THPT"
    },
    {
      "stt": "4",
      "nganh": "Quản lý tài nguyên và môi trường (Chương trình tiên tiến)",
      "diem_chuan": "17.00",
      "he_dao_tao": "Đại học",
      "khoi_thi": "B00,B08,D10,D01",
      "ghi_chu": "Xét duyệt điểm thi THPT"
    },
    {
      "stt": "5",
      "nganh": "Quốc tế học (Chương trình dạy và học bằng tiếng Anh)",
      "diem_chuan": "17.00",
      "he_dao_tao": "Đại học",
      "khoi_thi": "C00,A01,D01,D15",
      "ghi_chu": "Xét duyệt điểm thi THPT"
    },
    {
      "stt": "6",
      "nganh": "Công nghệ tài chính (Chương trình dạy và học bằng tiếng Anh)",
      "diem_chuan": "17.00",
      "he_dao_tao": "Đại học",
      "khoi_thi": "A00,A01,D01,D10",
      "ghi_chu": "Xét duyệt điểm thi THPT"
    },
    {
      "stt": "7",
      "nganh": "Kinh doanh quốc tế (Chương trình tiên tiến)",
      "diem_chuan": "17.00",
      "he_dao_tao": "Đại học",
      "khoi_thi": "A00,A01,D10,D01",
      "ghi_chu": "Xét kết quả học tập cấp THPT"
    },
    {
      "stt": "8",
      "nganh": "Quản trị kinh doanh (Chương trình tiên tiến)",
      "diem_chuan": "17.00",
      "he_dao_tao": "Đại học",
      "khoi_thi": "A00,A01,D10,D01",
      "ghi_chu": "Xét kết quả học tập cấp THPT"
    },
    {
      "stt": "9",
      "nganh": "Kế toán (Chương trình tiên tiến)",
      "diem_chuan": "17.00",
      "he_dao_tao": "Đại học",
      "khoi_thi": "A00,A01,D10,D01",
      "ghi_chu": "Xét kết quả học tập cấp THPT"
    },
    {
      "stt": "10",
      "nganh": "Quản lý tài nguyên và môi trường (Chương trình tiên tiến)",
      "diem_chuan": "17.00",
      "he_dao_tao": "Đại học",
      "khoi_thi": "B00,B08,D10,D01",
      "ghi_chu": "Xét kết quả học tập cấp THPT"
    },
    {
      "stt": "11",
      "nganh": "Quốc tế học (Chương trình dạy và học bằng tiếng Anh)",
      "diem_chuan": "17.00",
      "he_dao_tao": "Đại học",
      "khoi_thi": "C00,A01,D01,D15",
      "ghi_chu": "Xét kết quả học tập cấp THPT"
    },
    {
      "stt": "12",
      "nganh": "Công nghệ tài chính (Chương trình dạy và học bằng tiếng Anh)",
      "diem_chuan": "17.00",
      "he_dao_tao": "Đại học",
      "khoi_thi": "A00,A01,D01,D10",
      "ghi_chu": "Xét kết quả học tập cấp THPT"
    }
  ]
}