{
  "ten_truong": "Đại học Văn hóa Hà Nội",
  "ma_truong": "VHH",
  "url": "https://vietnamnet.vn/giao-duc/diem-thi/tra-cuu-diem-chuan-cd-dh-2023/truong/dai-hoc-van-hoa-ha-noi?keyword=VHH",
  "phuong_thuc_tuyen_sinh": "",
  "cac_nganh_dao_tao": [
    {
      "stt": "1",
      "nganh": "Ngôn ngữ Anh",
      "diem_chuan": "32.93",
      "he_dao_tao": "Đại học",
      "khoi_thi": "A00,A16,D01,D78,D96",
      "ghi_chu": ""
    },
    {
      "stt": "2",
      "nganh": "Du lịch - Hướng dẫn du lịch quốc tế",
      "diem_chuan": "31.40",
      "he_dao_tao": "Đại học",
      "khoi_thi": "A00,A16,D01,D78,D96",
      "ghi_chu": ""
    },
    {
      "stt": "3",
      "nganh": "Quản lý văn hoá - Tổ chức sự kiện văn hoá",
      "diem_chuan": "26.13",
      "he_dao_tao": "Đại học",
      "khoi_thi": "A00,A16,D01,D78,D96",
      "ghi_chu": ""
    },
    {
      "stt": "4",
      "nganh": "Quản lý văn hoá - Tổ chức sự kiện văn hoá",
      "diem_chuan": "26.13",
      "he_dao_tao": "Đại học",
      "khoi_thi": "C00",
      "ghi_chu": ""
    },
    {
      "stt": "5",
      "nganh": "Báo chí",
      "diem_chuan": "25.85",
      "he_dao_tao": "Đại học",
      "khoi_thi": "A00,A16,D01,D78,D96",
      "ghi_chu": ""
    },
    {
      "stt": "6",
      "nganh": "Báo chí",
      "diem_chuan": "25.85",
      "he_dao_tao": "Đại học",
      "khoi_thi": "C00",
      "ghi_chu": ""
    },
    {
      "stt": "7",
      "nganh": "Quản trị dịch vụ du lịch và lữ hành",
      "diem_chuan": "25.50",
      "he_dao_tao": "Đại học",
      "khoi_thi": "C00",
      "ghi_chu": ""
    },
    {
      "stt": "8",
      "nganh": "Quản trị dịch vụ du lịch và lữ hành",
      "diem_chuan": "25.50",
      "he_dao_tao": "Đại học",
      "khoi_thi": "A00,A16,D01,D78,D96",
      "ghi_chu": ""
    },
    {
      "stt": "9",
      "nganh": "Văn hoá học - Văn hoá truyền thông",
      "diem_chuan": "25.18",
      "he_dao_tao": "Đại học",
      "khoi_thi": "C00",
      "ghi_chu": ""
    },
    {
      "stt": "10",
      "nganh": "Văn hoá học - Văn hoá truyền thông",
      "diem_chuan": "25.18",
      "he_dao_tao": "Đại học",
      "khoi_thi": "A00,A16,D01,D78,D96",
      "ghi_chu": ""
    },
    {
      "stt": "11",
      "nganh": "Ngành Luật",
      "diem_chuan": "25.17",
      "he_dao_tao": "Đại học",
      "khoi_thi": "C00",
      "ghi_chu": ""
    },
    {
      "stt": "12",
      "nganh": "Ngành Luật",
      "diem_chuan": "25.17",
      "he_dao_tao": "Đại học",
      "khoi_thi": "A00,A16,D01,D78,D96",
      "ghi_chu": ""
    },
    {
      "stt": "13",
      "nganh": "Du lịch - Lữ hành, Hướng dẫn du lịch",
      "diem_chuan": "24.80",
      "he_dao_tao": "Đại học",
      "khoi_thi": "C00",
      "ghi_chu": ""
    },
    {
      "stt": "14",
      "nganh": "Du lịch - Lữ hành, Hướng dẫn du lịch",
      "diem_chuan": "24.80",
      "he_dao_tao": "Đại học",
      "khoi_thi": "A00,A16,D01,D78,D96",
      "ghi_chu": ""
    },
    {
      "stt": "15",
      "nganh": "Du lịch - Văn hóa du lịch",
      "diem_chuan": "24.41",
      "he_dao_tao": "Đại học",
      "khoi_thi": "C00",
      "ghi_chu": ""
    },
    {
      "stt": "16",
      "nganh": "Du lịch - Văn hóa du lịch",
      "diem_chuan": "24.41",
      "he_dao_tao": "Đại học",
      "khoi_thi": "A00,A16,D01,D78,D96",
      "ghi_chu": ""
    },
    {
      "stt": "17",
      "nganh": "Quản lý văn hóa, chuyên ngành (1) Quản lý hoạt động Văn hóa Xã hội",
      "diem_chuan": "23.96",
      "he_dao_tao": "Đại học",
      "khoi_thi": "C00",
      "ghi_chu": ""
    },
    {
      "stt": "18",
      "nganh": "Quản lý văn hóa, chuyên ngành (1) Quản lý hoạt động Văn hóa Xã hội",
      "diem_chuan": "23.96",
      "he_dao_tao": "Đại học",
      "khoi_thi": "A00,A16,D01,D78,D96",
      "ghi_chu": ""
    },
    {
      "stt": "19",
      "nganh": "Văn hóa học, chuyên ngành Truyền thông Văn hóa",
      "diem_chuan": "23.68",
      "he_dao_tao": "Đại học",
      "khoi_thi": "A00,A16,D01,D78,D96",
      "ghi_chu": ""
    },
    {
      "stt": "20",
      "nganh": "Văn hóa học, chuyên ngành Truyền thông Văn hóa",
      "diem_chuan": "23.68",
      "he_dao_tao": "Đại học",
      "khoi_thi": "C00",
      "ghi_chu": ""
    }
  ]
}